flask_heroku.py
setup.py
Flask_Heroku_Env.egg-info/PKG-INFO
Flask_Heroku_Env.egg-info/SOURCES.txt
Flask_Heroku_Env.egg-info/dependency_links.txt
Flask_Heroku_Env.egg-info/not-zip-safe
Flask_Heroku_Env.egg-info/requires.txt
Flask_Heroku_Env.egg-info/top_level.txt