Metadata-Version: 1.1
Name: Flask-Heroku-Env
Version: 0.0.4
Summary: Easily fetch Heroku environment variables.
Home-page: https://github.com/cburmeister/flask-heroku-env
Author: Corey Burmeister
Author-email: cburmeister@discogs.com
License: MIT
Platform: any
Classifier: Environment :: Web Environment
Classifier: Intended Audience :: Developers
Classifier: Programming Language :: Python
Classifier: Topic :: Internet :: WWW/HTTP :: Dynamic Content
Classifier: Topic :: Software Development :: Libraries :: Python Modules
